{"stem":"3986","instances":[{"docId":"TEI.teidata.pointer","docUri":"TEI.teidata.pointer.html","score":1,"contexts":[{"form":"3986","weight":"1","pos":99,"context":"...range of syntactically valid values is defined by RFC <mark>3986<\/mark> Uniform Resource Identifier (URI): Generic Syntax....","fid":"_d2e101341"}]},{"docId":"TEI.idno","docUri":"TEI.idno.html","score":1,"contexts":[{"form":"3986","weight":"1","pos":151,"context":"...identify a resource, following the syntax of RFC <mark>3986<\/mark>.","fid":"_d2e36127"}]},{"docId":"TEI.teidata.prefix","docUri":"TEI.teidata.prefix.html","score":1,"contexts":[{"form":"3986","weight":"1","pos":27,"context":"...used as a URI scheme name according to RFC <mark>3986<\/mark>, section 3.1. Thus only the 26 lowercase...","fid":"_d2e101403"}]}]}