{"stem":"access","instances":[{"docId":"TEI.head","docUri":"TEI.head.html","score":1,"contexts":[{"form":"accessibility","weight":"1","pos":301,"context":"...(hidden) A heading that is hidden (for <mark>accessibility<\/mark> purposes).","fid":"_d2e30988"}]},{"docId":"TEI.idno","docUri":"TEI.idno.html","score":1,"contexts":[{"form":"accessing","weight":"1","pos":158,"context":"...resource which usually contains indication of the means of <mark>accessing<\/mark> that resource, the name of its host,...","fid":"_d2e32178"}]}]}