{"stem":"addnam","instances":[{"docId":"TEI.addName","docUri":"TEI.addName.html","score":4,"contexts":[{"form":"addName","weight":"2","pos":1,"context":"&lt;<mark>addName<\/mark>&gt;"},{"form":"addName","weight":"1","pos":116,"context":"namesdates: <mark>addName<\/mark> affiliation birth death faith floruit forename genName langKnown nameLink...","fid":"_d2e8016"},{"form":"addName","weight":"1","pos":201,"context":"namesdates: <mark>addName<\/mark> affiliation forename genName geo location nameLink objectName orgName persName...","fid":"_d2e8272"}]},{"docId":"TEI.roleName","docUri":"TEI.roleName.html","score":3,"contexts":[{"form":"addName","weight":"1","pos":115,"context":"namesdates: <mark>addName<\/mark> affiliation birth death faith floruit forename genName langKnown nameLink...","fid":"_d2e68613"},{"form":"addName","weight":"1","pos":200,"context":"namesdates: <mark>addName<\/mark> affiliation forename genName geo location nameLink objectName orgName persName...","fid":"_d2e68869"},{"form":"addName","weight":"1","pos":225,"context":"A roleName may be distinguished from an <mark>addName<\/mark> by virtue of the fact that, like a title...","fid":"_d2e68936"}]},{"docId":"TEI.orgName","docUri":"TEI.orgName.html","score":2,"contexts":[{"form":"addName","weight":"1","pos":189,"context":"namesdates: <mark>addName<\/mark> affiliation birth death faith floruit forename genName langKnown nameLink...","fid":"_d2e55779"},{"form":"addName","weight":"1","pos":275,"context":"namesdates: <mark>addName<\/mark> affiliation forename genName geo location nameLink objectName orgName persName...","fid":"_d2e56038"}]},{"docId":"TEI.title","docUri":"TEI.title.html","score":2,"contexts":[{"form":"addName","weight":"1","pos":361,"context":"namesdates: <mark>addName<\/mark> affiliation birth death faith floruit forename genName langKnown nameLink...","fid":"_d2e80837"},{"form":"addName","weight":"1","pos":455,"context":"namesdates: <mark>addName<\/mark> affiliation forename genName geo listObject listOrg listPerson listPlace location...","fid":"_d2e81124"}]},{"docId":"TEI.sic","docUri":"TEI.sic.html","score":2,"contexts":[{"form":"addName","weight":"1","pos":99,"context":"namesdates: <mark>addName<\/mark> affiliation birth death faith floruit forename genName nameLink nationality...","fid":"_d2e73005"},{"form":"addName","weight":"1","pos":192,"context":"namesdates: <mark>addName<\/mark> affiliation forename genName geo listObject listOrg listPerson listPlace location...","fid":"_d2e73289"}]},{"docId":"TEI.surname","docUri":"TEI.surname.html","score":2,"contexts":[{"form":"addName","weight":"1","pos":111,"context":"namesdates: <mark>addName<\/mark> affiliation birth death faith floruit forename genName langKnown nameLink...","fid":"_d2e76947"},{"form":"addName","weight":"1","pos":196,"context":"namesdates: <mark>addName<\/mark> affiliation forename genName geo location nameLink objectName orgName persName...","fid":"_d2e77203"}]},{"docId":"TEI.objectName","docUri":"TEI.objectName.html","score":2,"contexts":[{"form":"addName","weight":"1","pos":192,"context":"namesdates: <mark>addName<\/mark> affiliation birth death faith floruit forename genName langKnown nameLink...","fid":"_d2e54071"},{"form":"addName","weight":"1","pos":278,"context":"namesdates: <mark>addName<\/mark> affiliation forename genName geo location nameLink objectName orgName persName...","fid":"_d2e54330"}]},{"docId":"TEI.genName","docUri":"TEI.genName.html","score":2,"contexts":[{"form":"addName","weight":"1","pos":118,"context":"namesdates: <mark>addName<\/mark> affiliation birth death faith floruit forename genName langKnown nameLink...","fid":"_d2e31758"},{"form":"addName","weight":"1","pos":203,"context":"namesdates: <mark>addName<\/mark> affiliation forename genName geo location nameLink objectName orgName persName...","fid":"_d2e32014"}]},{"docId":"TEI.num","docUri":"TEI.num.html","score":2,"contexts":[{"form":"addName","weight":"1","pos":155,"context":"namesdates: <mark>addName<\/mark> affiliation birth death faith floruit forename genName langKnown location...","fid":"_d2e52951"},{"form":"addName","weight":"1","pos":241,"context":"namesdates: <mark>addName<\/mark> affiliation forename genName geo location nameLink objectName orgName persName...","fid":"_d2e53210"}]},{"docId":"TEI.rs","docUri":"TEI.rs.html","score":2,"contexts":[{"form":"addName","weight":"1","pos":177,"context":"namesdates: <mark>addName<\/mark> affiliation birth death faith floruit forename genName langKnown nameLink...","fid":"_d2e69424"},{"form":"addName","weight":"1","pos":262,"context":"namesdates: <mark>addName<\/mark> affiliation forename genName geo location nameLink objectName orgName persName...","fid":"_d2e69680"}]},{"docId":"TEI.quote","docUri":"TEI.quote.html","score":2,"contexts":[{"form":"addName","weight":"1","pos":104,"context":"namesdates: <mark>addName<\/mark> affiliation birth death faith floruit forename genName nameLink nationality...","fid":"_d2e64394"},{"form":"addName","weight":"1","pos":200,"context":"namesdates: <mark>addName<\/mark> affiliation forename genName geo listObject listOrg listPerson listPlace location...","fid":"_d2e64692"}]},{"docId":"TEI.settlement","docUri":"TEI.settlement.html","score":2,"contexts":[{"form":"addName","weight":"1","pos":191,"context":"namesdates: <mark>addName<\/mark> affiliation birth death faith floruit forename genName langKnown location...","fid":"_d2e72062"},{"form":"addName","weight":"1","pos":277,"context":"namesdates: <mark>addName<\/mark> affiliation forename genName geo location nameLink objectName orgName persName...","fid":"_d2e72321"}]},{"docId":"TEI.mentioned","docUri":"TEI.mentioned.html","score":2,"contexts":[{"form":"addName","weight":"1","pos":93,"context":"namesdates: <mark>addName<\/mark> affiliation birth death faith floruit forename genName langKnown nameLink...","fid":"_d2e45872"},{"form":"addName","weight":"1","pos":178,"context":"namesdates: <mark>addName<\/mark> affiliation forename genName geo location nameLink objectName orgName persName...","fid":"_d2e46128"}]},{"docId":"TEI.nameLink","docUri":"TEI.nameLink.html","score":2,"contexts":[{"form":"addName","weight":"1","pos":106,"context":"namesdates: <mark>addName<\/mark> affiliation birth death faith floruit forename genName langKnown nameLink...","fid":"_d2e49437"},{"form":"addName","weight":"1","pos":191,"context":"namesdates: <mark>addName<\/mark> affiliation forename genName geo location nameLink objectName orgName persName...","fid":"_d2e49693"}]},{"docId":"TEI.orig","docUri":"TEI.orig.html","score":2,"contexts":[{"form":"addName","weight":"1","pos":98,"context":"namesdates: <mark>addName<\/mark> affiliation birth death faith floruit forename genName nameLink nationality...","fid":"_d2e56409"},{"form":"addName","weight":"1","pos":191,"context":"namesdates: <mark>addName<\/mark> affiliation forename genName geo listObject listOrg listPerson listPlace location...","fid":"_d2e56693"}]},{"docId":"TEI.persName","docUri":"TEI.persName.html","score":2,"contexts":[{"form":"addName","weight":"1","pos":207,"context":"namesdates: <mark>addName<\/mark> affiliation birth death faith floruit forename genName langKnown nameLink...","fid":"_d2e59105"},{"form":"addName","weight":"1","pos":294,"context":"namesdates: <mark>addName<\/mark> affiliation forename genName geo location nameLink objectName orgName persName...","fid":"_d2e59367"}]},{"docId":"TEI.note","docUri":"TEI.note.html","score":2,"contexts":[{"form":"addName","weight":"1","pos":185,"context":"namesdates: <mark>addName<\/mark> affiliation birth death faith floruit forename genName langKnown location...","fid":"_d2e50750"},{"form":"addName","weight":"1","pos":298,"context":"namesdates: <mark>addName<\/mark> affiliation forename genName geo listObject listOrg listPerson listPlace location...","fid":"_d2e51103"}]},{"docId":"TEI.term","docUri":"TEI.term.html","score":2,"contexts":[{"form":"addName","weight":"1","pos":111,"context":"namesdates: <mark>addName<\/mark> affiliation birth death faith floruit forename genName langKnown nameLink...","fid":"_d2e79055"},{"form":"addName","weight":"1","pos":196,"context":"namesdates: <mark>addName<\/mark> affiliation forename genName geo location nameLink objectName orgName persName...","fid":"_d2e79311"}]},{"docId":"TEI.time","docUri":"TEI.time.html","score":2,"contexts":[{"form":"addName","weight":"1","pos":91,"context":"namesdates: <mark>addName<\/mark> affiliation birth death faith floruit forename genName langKnown nameLink...","fid":"_d2e80049"},{"form":"addName","weight":"1","pos":174,"context":"namesdates: <mark>addName<\/mark> affiliation forename genName geo location nameLink objectName orgName persName...","fid":"_d2e80299"}]},{"docId":"TEI.damage","docUri":"TEI.damage.html","score":2,"contexts":[{"form":"addName","weight":"1","pos":117,"context":"namesdates: <mark>addName<\/mark> affiliation birth death faith floruit forename genName nameLink nationality...","fid":"_d2e17186"},{"form":"addName","weight":"1","pos":211,"context":"namesdates: <mark>addName<\/mark> affiliation forename genName geo listObject listOrg listPerson listPlace location...","fid":"_d2e17473"}]},{"docId":"TEI.supplied","docUri":"TEI.supplied.html","score":2,"contexts":[{"form":"addName","weight":"1","pos":115,"context":"namesdates: <mark>addName<\/mark> affiliation birth death faith floruit forename genName nameLink nationality...","fid":"_d2e75544"},{"form":"addName","weight":"1","pos":208,"context":"namesdates: <mark>addName<\/mark> affiliation forename genName geo listObject listOrg listPerson listPlace location...","fid":"_d2e75828"}]},{"docId":"TEI.placeName","docUri":"TEI.placeName.html","score":2,"contexts":[{"form":"addName","weight":"1","pos":195,"context":"namesdates: <mark>addName<\/mark> affiliation birth death faith floruit forename genName langKnown location...","fid":"_d2e60739"},{"form":"addName","weight":"1","pos":282,"context":"namesdates: <mark>addName<\/mark> affiliation forename genName geo location nameLink objectName orgName persName...","fid":"_d2e61001"}]},{"docId":"TEI.gloss","docUri":"TEI.gloss.html","score":2,"contexts":[{"form":"addName","weight":"1","pos":110,"context":"namesdates: <mark>addName<\/mark> affiliation birth death faith floruit forename genName langKnown nameLink...","fid":"_d2e32812"},{"form":"addName","weight":"1","pos":195,"context":"namesdates: <mark>addName<\/mark> affiliation forename genName geo location nameLink objectName orgName persName...","fid":"_d2e33068"}]},{"docId":"TEI.emph","docUri":"TEI.emph.html","score":2,"contexts":[{"form":"addName","weight":"1","pos":106,"context":"namesdates: <mark>addName<\/mark> affiliation birth death faith floruit forename genName langKnown nameLink...","fid":"_d2e24109"},{"form":"addName","weight":"1","pos":200,"context":"namesdates: <mark>addName<\/mark> affiliation forename genName geo listObject listOrg listPerson listPlace location...","fid":"_d2e24396"}]},{"docId":"TEI.hi","docUri":"TEI.hi.html","score":2,"contexts":[{"form":"addName","weight":"1","pos":113,"context":"namesdates: <mark>addName<\/mark> affiliation birth death faith floruit forename genName langKnown nameLink...","fid":"_d2e35460"},{"form":"addName","weight":"1","pos":208,"context":"namesdates: <mark>addName<\/mark> affiliation forename genName geo listObject listOrg listPerson listPlace location...","fid":"_d2e35750"}]},{"docId":"TEI.unclear","docUri":"TEI.unclear.html","score":2,"contexts":[{"form":"addName","weight":"1","pos":195,"context":"namesdates: <mark>addName<\/mark> affiliation birth death faith floruit forename genName nameLink nationality...","fid":"_d2e82993"},{"form":"addName","weight":"1","pos":289,"context":"namesdates: <mark>addName<\/mark> affiliation forename genName geo listObject listOrg listPerson listPlace location...","fid":"_d2e83280"}]},{"docId":"TEI.affiliation","docUri":"TEI.affiliation.html","score":2,"contexts":[{"form":"addName","weight":"1","pos":210,"context":"namesdates: <mark>addName<\/mark> affiliation birth death faith floruit forename genName langKnown location...","fid":"_d2e9007"},{"form":"addName","weight":"1","pos":298,"context":"namesdates: <mark>addName<\/mark> affiliation forename genName geo location nameLink objectName orgName persName...","fid":"_d2e9273"}]},{"docId":"TEI.del","docUri":"TEI.del.html","score":2,"contexts":[{"form":"addName","weight":"1","pos":124,"context":"namesdates: <mark>addName<\/mark> affiliation birth death faith floruit forename genName nameLink nationality...","fid":"_d2e19278"},{"form":"addName","weight":"1","pos":219,"context":"namesdates: <mark>addName<\/mark> affiliation forename genName geo listObject listOrg listPerson listPlace location...","fid":"_d2e19568"}]},{"docId":"TEI.add","docUri":"TEI.add.html","score":2,"contexts":[{"form":"addName","weight":"1","pos":121,"context":"namesdates: <mark>addName<\/mark> affiliation birth death faith floruit forename genName nameLink nationality...","fid":"_d2e7328"},{"form":"addName","weight":"1","pos":216,"context":"namesdates: <mark>addName<\/mark> affiliation forename genName geo listObject listOrg listPerson listPlace location...","fid":"_d2e7618"}]},{"docId":"TEI.foreign","docUri":"TEI.foreign.html","score":2,"contexts":[{"form":"addName","weight":"1","pos":99,"context":"namesdates: <mark>addName<\/mark> affiliation birth death faith floruit forename genName langKnown nameLink...","fid":"_d2e28280"},{"form":"addName","weight":"1","pos":184,"context":"namesdates: <mark>addName<\/mark> affiliation forename genName geo location nameLink objectName orgName persName...","fid":"_d2e28536"}]},{"docId":"TEI.date","docUri":"TEI.date.html","score":2,"contexts":[{"form":"addName","weight":"1","pos":116,"context":"namesdates: <mark>addName<\/mark> affiliation birth death faith floruit forename genName langKnown nameLink...","fid":"_d2e17923"},{"form":"addName","weight":"1","pos":199,"context":"namesdates: <mark>addName<\/mark> affiliation forename genName geo location nameLink objectName orgName persName...","fid":"_d2e18173"}]},{"docId":"TEI.name","docUri":"TEI.name.html","score":2,"contexts":[{"form":"addName","weight":"1","pos":215,"context":"namesdates: <mark>addName<\/mark> affiliation birth death faith floruit forename genName langKnown nameLink...","fid":"_d2e48748"},{"form":"addName","weight":"1","pos":300,"context":"namesdates: <mark>addName<\/mark> affiliation forename genName geo location nameLink objectName orgName persName...","fid":"_d2e49004"}]},{"docId":"TEI.q","docUri":"TEI.q.html","score":2,"contexts":[{"form":"addName","weight":"1","pos":101,"context":"namesdates: <mark>addName<\/mark> affiliation birth death faith floruit forename genName langKnown nameLink...","fid":"_d2e63607"},{"form":"addName","weight":"1","pos":202,"context":"namesdates: <mark>addName<\/mark> affiliation forename genName geo listObject listOrg listPerson listPlace location...","fid":"_d2e63920"}]},{"docId":"TEI.forename","docUri":"TEI.forename.html","score":2,"contexts":[{"form":"addName","weight":"1","pos":107,"context":"namesdates: <mark>addName<\/mark> affiliation birth death faith floruit forename genName langKnown nameLink...","fid":"_d2e28925"},{"form":"addName","weight":"1","pos":192,"context":"namesdates: <mark>addName<\/mark> affiliation forename genName geo location nameLink objectName orgName persName...","fid":"_d2e29181"}]},{"docId":"TEI.fw","docUri":"TEI.fw.html","score":2,"contexts":[{"form":"addName","weight":"1","pos":169,"context":"namesdates: <mark>addName<\/mark> affiliation birth death faith floruit forename genName langKnown nameLink...","fid":"_d2e29915"},{"form":"addName","weight":"1","pos":268,"context":"namesdates: <mark>addName<\/mark> affiliation forename genName geo location nameLink objectName orgName persName...","fid":"_d2e30216"}]},{"docId":"TEI.ref","docUri":"TEI.ref.html","score":2,"contexts":[{"form":"addName","weight":"1","pos":117,"context":"namesdates: <mark>addName<\/mark> affiliation birth death faith floruit forename genName langKnown nameLink...","fid":"_d2e65084"},{"form":"addName","weight":"1","pos":211,"context":"namesdates: <mark>addName<\/mark> affiliation forename genName geo listObject listOrg listPerson listPlace location...","fid":"_d2e65371"}]},{"docId":"TEI.abbr","docUri":"TEI.abbr.html","score":2,"contexts":[{"form":"addName","weight":"1","pos":204,"context":"namesdates: <mark>addName<\/mark> affiliation birth death faith floruit forename genName langKnown nameLink...","fid":"_d2e6093"},{"form":"addName","weight":"1","pos":289,"context":"namesdates: <mark>addName<\/mark> affiliation forename genName geo location nameLink objectName orgName persName...","fid":"_d2e6349"}]},{"docId":"TEI.reg","docUri":"TEI.reg.html","score":2,"contexts":[{"form":"addName","weight":"1","pos":100,"context":"namesdates: <mark>addName<\/mark> affiliation birth death faith floruit forename genName nameLink nationality...","fid":"_d2e65759"},{"form":"addName","weight":"1","pos":193,"context":"namesdates: <mark>addName<\/mark> affiliation forename genName geo listObject listOrg listPerson listPlace location...","fid":"_d2e66043"}]},{"docId":"TEI.pc","docUri":"TEI.pc.html","score":1,"contexts":[{"form":"addName","weight":"1","pos":108,"context":"namesdates: <mark>addName<\/mark> affiliation birth death faith floruit forename genName nameLink nationality...","fid":"_d2e58542"}]},{"docId":"TEI.label","docUri":"TEI.label.html","score":1,"contexts":[{"form":"addName","weight":"1","pos":153,"context":"namesdates: <mark>addName<\/mark> affiliation forename genName geo location nameLink objectName orgName persName...","fid":"_d2e38508"}]},{"docId":"TEI.dateline","docUri":"TEI.dateline.html","score":1,"contexts":[{"form":"addName","weight":"1","pos":109,"context":"namesdates: <mark>addName<\/mark> affiliation forename genName geo location nameLink objectName orgName persName...","fid":"_d2e18507"}]},{"docId":"TEI.location","docUri":"TEI.location.html","score":1,"contexts":[{"form":"addName","weight":"1","pos":186,"context":"namesdates: <mark>addName<\/mark> affiliation birth death faith floruit forename genName langKnown nameLink...","fid":"_d2e44535"}]},{"docId":"TEI.p","docUri":"TEI.p.html","score":1,"contexts":[{"form":"addName","weight":"1","pos":145,"context":"namesdates: <mark>addName<\/mark> affiliation forename genName geo listObject listOrg listPerson listPlace location...","fid":"_d2e57665"}]},{"docId":"TEI.lb","docUri":"TEI.lb.html","score":1,"contexts":[{"form":"addName","weight":"1","pos":115,"context":"namesdates: <mark>addName<\/mark> affiliation birth death faith floruit forename genName langKnown nameLink...","fid":"_d2e40069"}]},{"docId":"TEI.w","docUri":"TEI.w.html","score":1,"contexts":[{"form":"addName","weight":"1","pos":92,"context":"namesdates: <mark>addName<\/mark> affiliation birth death faith floruit forename genName nameLink nationality...","fid":"_d2e83734"}]},{"docId":"TEI.att.global.source","docUri":"TEI.att.global.source.html","score":1,"contexts":[{"form":"addName","weight":"1","pos":30,"context":"...global [NB TEI ab abbr abstract activity add <mark>addName<\/mark> additional adminInfo affiliation author bibl biblStruct body byline catDesc..."}]},{"docId":"TEI.langKnown","docUri":"TEI.langKnown.html","score":1,"contexts":[{"form":"addName","weight":"1","pos":175,"context":"namesdates: <mark>addName<\/mark> affiliation forename genName geo location nameLink objectName orgName persName...","fid":"_d2e39233"}]},{"docId":"TEI.att.global.rendition","docUri":"TEI.att.global.rendition.html","score":1,"contexts":[{"form":"addName","weight":"1","pos":26,"context":"...global [NB TEI ab abbr abstract activity add <mark>addName<\/mark> additional adminInfo affiliation author bibl biblStruct body byline catDesc..."}]},{"docId":"TEI.rule","docUri":"TEI.rule.html","score":1,"contexts":[{"form":"addName","weight":"1","pos":151,"context":"namesdates: <mark>addName<\/mark> affiliation birth death faith floruit forename genName langKnown nameLink...","fid":"_d2e70162"}]},{"docId":"TEI.language","docUri":"TEI.language.html","score":1,"contexts":[{"form":"addName","weight":"1","pos":103,"context":"namesdates: <mark>addName<\/mark> affiliation forename genName geo location nameLink objectName orgName persName...","fid":"_d2e39666"}]},{"docId":"TEI.pubPlace","docUri":"TEI.pubPlace.html","score":1,"contexts":[{"form":"addName","weight":"1","pos":103,"context":"namesdates: <mark>addName<\/mark> affiliation forename genName geo location nameLink objectName orgName persName...","fid":"_d2e62582"}]},{"docId":"TEI.activity","docUri":"TEI.activity.html","score":1,"contexts":[{"form":"addName","weight":"1","pos":75,"context":"namesdates: <mark>addName<\/mark> affiliation forename genName geo location nameLink objectName orgName persName...","fid":"_d2e6959"}]},{"docId":"TEI.faith","docUri":"TEI.faith.html","score":1,"contexts":[{"form":"addName","weight":"1","pos":159,"context":"namesdates: <mark>addName<\/mark> affiliation forename genName geo location nameLink objectName orgName persName...","fid":"_d2e26404"}]},{"docId":"TEI.model.persNamePart","docUri":"TEI.model.persNamePart.html","score":1,"contexts":[{"form":"addName","weight":"1","pos":15,"context":"<mark>addName<\/mark> forename genName nameLink roleName surname"}]},{"docId":"TEI.att.naming","docUri":"TEI.att.naming.html","score":1,"contexts":[{"form":"addName","weight":"1","pos":22,"context":"att.personal [<mark>addName<\/mark> forename genName name objectName orgName persName placeName roleName surname..."}]},{"docId":"TEI.macro.phraseSeq","docUri":"TEI.macro.phraseSeq.html","score":1,"contexts":[{"form":"addName","weight":"1","pos":19,"context":"abbr <mark>addName<\/mark> affiliation author birth death docAuthor docDate editor expan extent...","fid":"_d2e99561"}]},{"docId":"TEI.att.global","docUri":"TEI.att.global.html","score":1,"contexts":[{"form":"addName","weight":"1","pos":22,"context":"NB TEI ab abbr abstract activity add <mark>addName<\/mark> additional adminInfo affiliation author bibl biblStruct body byline catDesc..."}]},{"docId":"TEI.enclosure","docUri":"TEI.enclosure.html","score":1,"contexts":[{"form":"addName","weight":"1","pos":83,"context":"namesdates: <mark>addName<\/mark> affiliation forename genName geo listObject listOrg listPerson listPlace location...","fid":"_d2e24749"}]},{"docId":"TEI.idno","docUri":"TEI.idno.html","score":1,"contexts":[{"form":"addName","weight":"1","pos":334,"context":"namesdates: <mark>addName<\/mark> affiliation birth death faith floruit forename genName langKnown nameLink...","fid":"_d2e36392"}]},{"docId":"TEI.byline","docUri":"TEI.byline.html","score":1,"contexts":[{"form":"addName","weight":"1","pos":106,"context":"namesdates: <mark>addName<\/mark> affiliation forename genName geo location nameLink objectName orgName persName...","fid":"_d2e11816"}]},{"docId":"TEI.pb","docUri":"TEI.pb.html","score":1,"contexts":[{"form":"addName","weight":"1","pos":104,"context":"namesdates: <mark>addName<\/mark> affiliation birth death faith floruit forename genName langKnown nameLink...","fid":"_d2e58060"}]},{"docId":"TEI.l","docUri":"TEI.l.html","score":1,"contexts":[{"form":"addName","weight":"1","pos":154,"context":"namesdates: <mark>addName<\/mark> affiliation forename genName geo listObject listOrg listPerson listPlace location...","fid":"_d2e38002"}]},{"docId":"TEI.cit","docUri":"TEI.cit.html","score":1,"contexts":[{"form":"addName","weight":"1","pos":116,"context":"namesdates: <mark>addName<\/mark> affiliation birth death faith floruit forename genName nameLink nationality...","fid":"_d2e14441"}]},{"docId":"TEI.gap","docUri":"TEI.gap.html","score":1,"contexts":[{"form":"addName","weight":"1","pos":195,"context":"namesdates: <mark>addName<\/mark> affiliation birth death faith floruit forename genName langKnown nameLink...","fid":"_d2e31157"}]},{"docId":"TEI.sex","docUri":"TEI.sex.html","score":1,"contexts":[{"form":"addName","weight":"1","pos":85,"context":"namesdates: <mark>addName<\/mark> affiliation forename genName geo location nameLink objectName orgName persName...","fid":"_d2e72645"}]},{"docId":"TEI.author","docUri":"TEI.author.html","score":1,"contexts":[{"form":"addName","weight":"1","pos":187,"context":"namesdates: <mark>addName<\/mark> affiliation forename genName geo location nameLink objectName orgName persName...","fid":"_d2e9751"}]},{"docId":"TEI.correspAction","docUri":"TEI.correspAction.html","score":1,"contexts":[{"form":"addName","weight":"1","pos":131,"context":"namesdates: <mark>addName<\/mark> affiliation forename genName location nameLink objectName orgName persName placeName...","fid":"_d2e16139"}]},{"docId":"TEI.floruit","docUri":"TEI.floruit.html","score":1,"contexts":[{"form":"addName","weight":"1","pos":174,"context":"namesdates: <mark>addName<\/mark> affiliation forename genName geo location nameLink objectName orgName persName...","fid":"_d2e27922"}]},{"docId":"TEI.residence","docUri":"TEI.residence.html","score":1,"contexts":[{"form":"addName","weight":"1","pos":117,"context":"namesdates: <mark>addName<\/mark> affiliation forename genName geo location nameLink objectName orgName persName...","fid":"_d2e67527"}]},{"docId":"TEI.docEdition","docUri":"TEI.docEdition.html","score":1,"contexts":[{"form":"addName","weight":"1","pos":101,"context":"namesdates: <mark>addName<\/mark> affiliation forename genName geo listObject listOrg listPerson listPlace location...","fid":"_d2e21968"}]},{"docId":"TEI.docImprint","docUri":"TEI.docImprint.html","score":1,"contexts":[{"form":"addName","weight":"1","pos":98,"context":"namesdates: <mark>addName<\/mark> affiliation forename genName geo location nameLink objectName orgName persName...","fid":"_d2e22305"}]},{"docId":"TEI.nationality","docUri":"TEI.nationality.html","score":1,"contexts":[{"form":"addName","weight":"1","pos":229,"context":"namesdates: <mark>addName<\/mark> affiliation forename genName geo location nameLink objectName orgName persName...","fid":"_d2e50142"}]},{"docId":"TEI.att.personal","docUri":"TEI.att.personal.html","score":1,"contexts":[{"form":"addName","weight":"1","pos":24,"context":"<mark>addName<\/mark> forename genName name objectName orgName persName placeName roleName surname..."}]},{"docId":"TEI.figDesc","docUri":"TEI.figDesc.html","score":1,"contexts":[{"form":"addName","weight":"1","pos":77,"context":"namesdates: <mark>addName<\/mark> affiliation forename genName geo listObject listOrg listPerson listPlace location...","fid":"_d2e26726"}]},{"docId":"TEI.att.canonical","docUri":"TEI.att.canonical.html","score":1,"contexts":[{"form":"addName","weight":"1","pos":24,"context":"att.naming [att.personal [<mark>addName<\/mark> forename genName name objectName orgName persName placeName roleName surname..."}]},{"docId":"TEI.att.typed","docUri":"TEI.att.typed.html","score":1,"contexts":[{"form":"addName","weight":"1","pos":93,"context":"TEI ab abbr add <mark>addName<\/mark> affiliation bibl biblStruct change cit collection corr correspAction correspDesc..."}]},{"docId":"TEI.publisher","docUri":"TEI.publisher.html","score":1,"contexts":[{"form":"addName","weight":"1","pos":106,"context":"namesdates: <mark>addName<\/mark> affiliation forename genName geo location nameLink objectName orgName persName...","fid":"_d2e63081"}]},{"docId":"TEI.occupation","docUri":"TEI.occupation.html","score":1,"contexts":[{"form":"addName","weight":"1","pos":231,"context":"namesdates: <mark>addName<\/mark> affiliation forename genName geo listObject listOrg listPerson listPlace location...","fid":"_d2e54875"}]},{"docId":"TEI.ptr","docUri":"TEI.ptr.html","score":1,"contexts":[{"form":"addName","weight":"1","pos":113,"context":"namesdates: <mark>addName<\/mark> affiliation birth death faith floruit forename genName langKnown nameLink...","fid":"_d2e62180"}]},{"docId":"TEI.locusGrp","docUri":"TEI.locusGrp.html","score":1,"contexts":[{"form":"addName","weight":"1","pos":127,"context":"namesdates: <mark>addName<\/mark> affiliation birth death faith floruit forename genName langKnown nameLink...","fid":"_d2e45310"}]},{"docId":"TEI.subst","docUri":"TEI.subst.html","score":1,"contexts":[{"form":"addName","weight":"1","pos":118,"context":"namesdates: <mark>addName<\/mark> affiliation birth death faith floruit forename genName langKnown nameLink...","fid":"_d2e74713"}]},{"docId":"TEI.model.limitedPhrase","docUri":"TEI.model.limitedPhrase.html","score":1,"contexts":[{"form":"addName","weight":"1","pos":63,"context":"...persName] model.offsetLike model.persNamePart [<mark>addName<\/mark> forename genName nameLink roleName surname] model.placeStateLike..."}]},{"docId":"TEI.geo","docUri":"TEI.geo.html","score":1,"contexts":[{"form":"addName","weight":"1","pos":104,"context":"namesdates: <mark>addName<\/mark> affiliation birth death faith floruit forename genName langKnown location...","fid":"_d2e32364"}]},{"docId":"TEI.g","docUri":"TEI.g.html","score":1,"contexts":[{"form":"addName","weight":"1","pos":104,"context":"namesdates: <mark>addName<\/mark> affiliation birth death faith floruit forename genName nameLink nationality...","fid":"_d2e30613"}]},{"docId":"TEI.head","docUri":"TEI.head.html","score":1,"contexts":[{"form":"addName","weight":"1","pos":383,"context":"namesdates: <mark>addName<\/mark> affiliation forename genName geo listObject listOrg listPerson listPlace location...","fid":"_d2e35002"}]},{"docId":"TEI.model.pPart.data","docUri":"TEI.model.pPart.data.html","score":1,"contexts":[{"form":"addName","weight":"1","pos":51,"context":"...persName] model.offsetLike model.persNamePart [<mark>addName<\/mark> forename genName nameLink roleName surname] model.placeStateLike..."}]},{"docId":"TEI.collection","docUri":"TEI.collection.html","score":1,"contexts":[{"form":"addName","weight":"1","pos":83,"context":"namesdates: <mark>addName<\/mark> affiliation forename genName geo location nameLink objectName orgName persName...","fid":"_d2e15074"}]},{"docId":"TEI.repository","docUri":"TEI.repository.html","score":1,"contexts":[{"form":"addName","weight":"1","pos":81,"context":"namesdates: <mark>addName<\/mark> affiliation forename genName geo location nameLink objectName orgName persName...","fid":"_d2e66766"}]},{"docId":"TEI.handNote","docUri":"TEI.handNote.html","score":1,"contexts":[{"form":"addName","weight":"1","pos":128,"context":"namesdates: <mark>addName<\/mark> affiliation forename genName geo listObject listOrg listPerson listPlace location...","fid":"_d2e33974"}]},{"docId":"TEI.compliment","docUri":"TEI.compliment.html","score":1,"contexts":[{"form":"addName","weight":"1","pos":89,"context":"namesdates: <mark>addName<\/mark> affiliation forename genName geo listObject listOrg listPerson listPlace location...","fid":"_d2e15421"}]},{"docId":"TEI.linkGrp","docUri":"TEI.linkGrp.html","score":1,"contexts":[{"form":"addName","weight":"1","pos":102,"context":"namesdates: <mark>addName<\/mark> affiliation birth death faith floruit forename genName langKnown nameLink...","fid":"_d2e41246"}]},{"docId":"TEI.origin","docUri":"TEI.origin.html","score":1,"contexts":[{"form":"addName","weight":"1","pos":175,"context":"namesdates: <mark>addName<\/mark> affiliation forename genName geo listObject listOrg listPerson listPlace location...","fid":"_d2e57146"}]},{"docId":"TEI.change","docUri":"TEI.change.html","score":1,"contexts":[{"form":"addName","weight":"1","pos":230,"context":"namesdates: <mark>addName<\/mark> affiliation forename genName geo listObject listOrg listPerson listPlace location...","fid":"_d2e13249"}]},{"docId":"TEI.model.correspActionPart","docUri":"TEI.model.correspActionPart.html","score":1,"contexts":[{"form":"addName","weight":"1","pos":36,"context":"...persName] model.offsetLike model.persNamePart [<mark>addName<\/mark> forename genName nameLink roleName surname] model.placeStateLike..."}]},{"docId":"TEI.figure","docUri":"TEI.figure.html","score":1,"contexts":[{"form":"addName","weight":"1","pos":119,"context":"namesdates: <mark>addName<\/mark> affiliation birth death faith floruit forename genName langKnown nameLink...","fid":"_d2e27119"}]},{"docId":"TEI.catDesc","docUri":"TEI.catDesc.html","score":1,"contexts":[{"form":"addName","weight":"1","pos":72,"context":"namesdates: <mark>addName<\/mark> affiliation forename genName geo location nameLink objectName orgName persName...","fid":"_d2e12082"}]},{"docId":"TEI.desc","docUri":"TEI.desc.html","score":1,"contexts":[{"form":"addName","weight":"1","pos":178,"context":"namesdates: <mark>addName<\/mark> affiliation forename genName geo listObject listOrg listPerson listPlace location...","fid":"_d2e20163"}]},{"docId":"TEI.duration","docUri":"TEI.duration.html","score":1,"contexts":[{"form":"addName","weight":"1","pos":64,"context":"namesdates: <mark>addName<\/mark> affiliation forename genName geo listObject listOrg listPerson listPlace location...","fid":"_d2e22837"}]},{"docId":"TEI.corr","docUri":"TEI.corr.html","score":1,"contexts":[{"form":"addName","weight":"1","pos":106,"context":"namesdates: <mark>addName<\/mark> affiliation forename genName geo listObject listOrg listPerson listPlace location...","fid":"_d2e15827"}]},{"docId":"TEI.editor","docUri":"TEI.editor.html","score":1,"contexts":[{"form":"addName","weight":"1","pos":183,"context":"namesdates: <mark>addName<\/mark> affiliation forename genName geo location nameLink objectName orgName persName...","fid":"_d2e23225"}]},{"docId":"TEI.salute","docUri":"TEI.salute.html","score":1,"contexts":[{"form":"addName","weight":"1","pos":117,"context":"namesdates: <mark>addName<\/mark> affiliation forename genName geo listObject listOrg listPerson listPlace location...","fid":"_d2e70785"}]},{"docId":"TEI.expan","docUri":"TEI.expan.html","score":1,"contexts":[{"form":"addName","weight":"1","pos":89,"context":"namesdates: <mark>addName<\/mark> affiliation forename genName geo location nameLink objectName orgName persName...","fid":"_d2e25512"}]},{"docId":"TEI.cell","docUri":"TEI.cell.html","score":1,"contexts":[{"form":"addName","weight":"1","pos":96,"context":"namesdates: <mark>addName<\/mark> affiliation forename genName geo listObject listOrg listPerson listPlace location...","fid":"_d2e12753"}]},{"docId":"TEI.surrogates","docUri":"TEI.surrogates.html","score":1,"contexts":[{"form":"addName","weight":"1","pos":98,"context":"namesdates: <mark>addName<\/mark> affiliation forename genName geo listObject listOrg listPerson listPlace location...","fid":"_d2e77546"}]},{"docId":"TEI.imprimatur","docUri":"TEI.imprimatur.html","score":1,"contexts":[{"form":"addName","weight":"1","pos":101,"context":"namesdates: <mark>addName<\/mark> affiliation forename genName geo listObject listOrg listPerson listPlace location...","fid":"_d2e36928"}]},{"docId":"TEI.death","docUri":"TEI.death.html","score":1,"contexts":[{"form":"addName","weight":"1","pos":104,"context":"namesdates: <mark>addName<\/mark> affiliation forename genName geo location nameLink objectName orgName persName...","fid":"_d2e18873"}]},{"docId":"TEI.graphic","docUri":"TEI.graphic.html","score":1,"contexts":[{"form":"addName","weight":"1","pos":117,"context":"namesdates: <mark>addName<\/mark> affiliation birth death faith floruit forename genName nameLink nationality...","fid":"_d2e33446"}]},{"docId":"TEI.rendition","docUri":"TEI.rendition.html","score":1,"contexts":[{"form":"addName","weight":"1","pos":192,"context":"namesdates: <mark>addName<\/mark> affiliation forename genName geo listObject listOrg listPerson listPlace location...","fid":"_d2e66439"}]},{"docId":"TEI.ellipsis","docUri":"TEI.ellipsis.html","score":1,"contexts":[{"form":"addName","weight":"1","pos":127,"context":"namesdates: <mark>addName<\/mark> affiliation birth death faith floruit forename genName langKnown nameLink...","fid":"_d2e23639"}]},{"docId":"TEI.extent","docUri":"TEI.extent.html","score":1,"contexts":[{"form":"addName","weight":"1","pos":111,"context":"namesdates: <mark>addName<\/mark> affiliation forename genName geo location nameLink objectName orgName persName...","fid":"_d2e25855"}]},{"docId":"TEI.docAuthor","docUri":"TEI.docAuthor.html","score":1,"contexts":[{"form":"addName","weight":"1","pos":110,"context":"namesdates: <mark>addName<\/mark> affiliation forename genName geo location nameLink objectName orgName persName...","fid":"_d2e21189"}]},{"docId":"TEI.milestone","docUri":"TEI.milestone.html","score":1,"contexts":[{"form":"addName","weight":"1","pos":149,"context":"namesdates: <mark>addName<\/mark> affiliation birth death faith floruit forename genName langKnown nameLink...","fid":"_d2e46706"}]},{"docId":"TEI.signed","docUri":"TEI.signed.html","score":1,"contexts":[{"form":"addName","weight":"1","pos":118,"context":"namesdates: <mark>addName<\/mark> affiliation forename genName geo listObject listOrg listPerson listPlace location...","fid":"_d2e73709"}]},{"docId":"TEI.resp","docUri":"TEI.resp.html","score":1,"contexts":[{"form":"addName","weight":"1","pos":167,"context":"namesdates: <mark>addName<\/mark> affiliation forename genName geo location nameLink objectName orgName persName...","fid":"_d2e67897"}]},{"docId":"TEI.model.nameLike","docUri":"TEI.model.nameLike.html","score":1,"contexts":[{"form":"addName","weight":"1","pos":26,"context":"...persName] model.offsetLike model.persNamePart [<mark>addName<\/mark> forename genName nameLink roleName surname] model.placeStateLike..."}]},{"docId":"TEI.noteGrp","docUri":"TEI.noteGrp.html","score":1,"contexts":[{"form":"addName","weight":"1","pos":135,"context":"namesdates: <mark>addName<\/mark> affiliation birth death faith floruit forename genName langKnown location...","fid":"_d2e51666"}]},{"docId":"TEI.ab","docUri":"TEI.ab.html","score":1,"contexts":[{"form":"addName","weight":"1","pos":163,"context":"namesdates: <mark>addName<\/mark> affiliation forename genName geo listObject listOrg listPerson listPlace location...","fid":"_d2e5609"}]},{"docId":"TEI.model.phrase","docUri":"TEI.model.phrase.html","score":1,"contexts":[{"form":"addName","weight":"1","pos":72,"context":"...persName] model.offsetLike model.persNamePart [<mark>addName<\/mark> forename genName nameLink roleName surname] model.placeStateLike..."}]},{"docId":"TEI.choice","docUri":"TEI.choice.html","score":1,"contexts":[{"form":"addName","weight":"1","pos":102,"context":"namesdates: <mark>addName<\/mark> affiliation birth death faith floruit forename genName langKnown nameLink...","fid":"_d2e13973"}]},{"docId":"TEI.docDate","docUri":"TEI.docDate.html","score":1,"contexts":[{"form":"addName","weight":"1","pos":129,"context":"namesdates: <mark>addName<\/mark> affiliation forename genName geo location nameLink objectName orgName persName...","fid":"_d2e21603"}]},{"docId":"TEI.lim.att.global.fragmentable","docUri":"TEI.lim.att.global.fragmentable.html","score":1,"contexts":[{"form":"addName","weight":"1","pos":25,"context":"...global [NB TEI ab abbr abstract activity add <mark>addName<\/mark> additional adminInfo affiliation author bibl biblStruct body byline catDesc..."}]},{"docId":"TEI.noteMarker","docUri":"TEI.noteMarker.html","score":1,"contexts":[{"form":"addName","weight":"1","pos":179,"context":"namesdates: <mark>addName<\/mark> affiliation birth death faith floruit forename genName langKnown nameLink...","fid":"_d2e52203"}]},{"docId":"TEI.handShift","docUri":"TEI.handShift.html","score":1,"contexts":[{"form":"addName","weight":"1","pos":131,"context":"namesdates: <mark>addName<\/mark> affiliation birth death faith floruit forename genName nameLink nationality...","fid":"_d2e34474"}]},{"docId":"TEI.seg","docUri":"TEI.seg.html","score":1,"contexts":[{"form":"addName","weight":"1","pos":83,"context":"namesdates: <mark>addName<\/mark> affiliation forename genName geo listObject listOrg listPerson listPlace location...","fid":"_d2e71311"}]},{"docId":"TEI.trailer","docUri":"TEI.trailer.html","score":1,"contexts":[{"form":"addName","weight":"1","pos":119,"context":"namesdates: <mark>addName<\/mark> affiliation forename genName geo listObject listOrg listPerson listPlace location...","fid":"_d2e82504"}]},{"docId":"TEI.item","docUri":"TEI.item.html","score":1,"contexts":[{"form":"addName","weight":"1","pos":97,"context":"namesdates: <mark>addName<\/mark> affiliation forename genName geo listObject listOrg listPerson listPlace location...","fid":"_d2e37461"}]},{"docId":"TEI.birth","docUri":"TEI.birth.html","score":1,"contexts":[{"form":"addName","weight":"1","pos":104,"context":"namesdates: <mark>addName<\/mark> affiliation forename genName geo location nameLink objectName orgName persName...","fid":"_d2e11080"}]},{"docId":"TEI.bibl","docUri":"TEI.bibl.html","score":1,"contexts":[{"form":"addName","weight":"1","pos":172,"context":"namesdates: <mark>addName<\/mark> affiliation forename genName geo location nameLink objectName orgName persName...","fid":"_d2e10310"}]},{"docId":"TEI.titlePart","docUri":"TEI.titlePart.html","score":1,"contexts":[{"form":"addName","weight":"1","pos":139,"context":"namesdates: <mark>addName<\/mark> affiliation forename genName geo listObject listOrg listPerson listPlace location...","fid":"_d2e81913"}]},{"docId":"TEI.model.paraPart","docUri":"TEI.model.paraPart.html","score":1,"contexts":[{"form":"addName","weight":"1","pos":123,"context":"...persName] model.offsetLike model.persNamePart [<mark>addName<\/mark> forename genName nameLink roleName surname] model.placeStateLike..."}]},{"docId":"TEI.summary","docUri":"TEI.summary.html","score":1,"contexts":[{"form":"addName","weight":"1","pos":109,"context":"namesdates: <mark>addName<\/mark> affiliation forename genName geo listObject listOrg listPerson listPlace location...","fid":"_d2e75194"}]},{"docId":"TEI.request","docUri":"TEI.request.html","score":1,"contexts":[{"form":"addName","weight":"1","pos":89,"context":"namesdates: <mark>addName<\/mark> affiliation forename genName geo listObject listOrg listPerson listPlace location...","fid":"_d2e67108"}]}]}