{"stem":"corrector","instances":[{"docId":"TEI.del","docUri":"TEI.del.html","score":1,"contexts":[{"form":"corrector","weight":"1","pos":20,"context":"...author, scribe, or a previous annotator or <mark>corrector<\/mark>. [3.5.3. Additions, Deletions, and...","fid":"_d2e19010"}]},{"docId":"TEI.add","docUri":"TEI.add.html","score":1,"contexts":[{"form":"corrector","weight":"1","pos":14,"context":"...author, scribe, or a previous annotator or <mark>corrector<\/mark>. [3.5.3. Additions, Deletions, and...","fid":"_d2e7054"}]}]}