{"stem":"inconsist","instances":[{"docId":"transcription_workflow","docUri":"transcription_workflow.html","score":20,"contexts":[{"form":"inconsistency","weight":"20","pos":340,"context":".... Often, these errors are caused by some <mark>inconsistency<\/mark> in the Transcription Roster, so double check that...","fid":"_d2e1032"}]},{"docId":"encoding_structure","docUri":"encoding_structure.html","score":20,"contexts":[{"form":"inconsistently","weight":"20","pos":30,"context":"Since headings appear <mark>inconsistently<\/mark> across the document collection and are often styled differently...","fid":"_d2e1605"}]}]}