{"stem":"instal","instances":[{"docId":"getting_started","docUri":"getting_started.html","score":3,"contexts":[{"form":"install","weight":"1","pos":11,"context":"...are two pieces of software you will need to <mark>install<\/mark>: oXygen XML Editor and Github Desktop. You...","fid":"_d2e470"},{"form":"install","weight":"1","pos":36,"context":"Download and <mark>install<\/mark> oXygen:https:\/\/www.oxygenxml.com...","fid":"_d2e485"},{"form":"install","weight":"1","pos":57,"context":"Download and <mark>install<\/mark> the GitHub desktop client: https:\/\/desktop....","fid":"_d2e494"}]}]}