{"stem":"ittf","instances":[{"docId":"TEI.persona","docUri":"TEI.persona.html","score":1,"contexts":[{"form":"ittf","weight":"1","pos":128,"context":"...Sexes http:\/\/standards.iso.org\/<mark>ittf<\/mark>\/PubliclyAvailableStandards\/c036266_ISO_IEC_...","fid":"_d2e52274"}]},{"docId":"TEI.teidata.sex","docUri":"TEI.teidata.sex.html","score":1,"contexts":[{"form":"ittf","weight":"1","pos":58,"context":"...Sexes http:\/\/standards.iso.org\/<mark>ittf<\/mark>\/PubliclyAvailableStandards\/c036266_ISO_IEC_...","fid":"_d2e89937"}]},{"docId":"TEI.sex","docUri":"TEI.sex.html","score":1,"contexts":[{"form":"ittf","weight":"1","pos":61,"context":"...Sexes http:\/\/standards.iso.org\/<mark>ittf<\/mark>\/PubliclyAvailableStandards\/c036266_ISO_IEC_...","fid":"_d2e62795"}]}]}