{"stem":"leith","instances":[{"docId":"encoding_structure","docUri":"encoding_structure.html","score":1,"contexts":[{"form":"Leith\"","weight":"1","pos":58,"context":"...Mr Robert Forbes at My Lady Bruce's Lodgings at <mark>Leith\"<\/mark>:","fid":"_d2e1600"}]},{"docId":"index","docUri":"index.html","score":1,"contexts":[{"form":"Leith","weight":"1","pos":20,"context":"...the larger SSHRC-funded Networking Jacobites project (<mark>Leith<\/mark> Davis [SFU, Department of English], Ralph...","fid":"_d2e361"}]}]}