{"stem":"ppart","instances":[{"docId":"TEI.model.phrase","docUri":"TEI.model.phrase.html","score":5,"contexts":[{"form":"pPart","weight":"1","pos":47,"context":"...[hi q] ] model.lPart model.<mark>pPart<\/mark>.data [model.addressLike [affiliation]..."},{"form":"pPart","weight":"1","pos":89,"context":"...location] idno objectName rs] ] model.<mark>pPart<\/mark>.edit [model.pPart.editorial [..."},{"form":"pPart","weight":"1","pos":92,"context":"...] model.pPart.edit [model.<mark>pPart<\/mark>.editorial [abbr choice subst] model...."},{"form":"pPart","weight":"1","pos":98,"context":"....editorial [abbr choice subst] model.<mark>pPart<\/mark>.transcriptional [add damage del handShift orig reg..."},{"form":"pPart","weight":"1","pos":110,"context":"...orig reg sic supplied unclear] ] model.<mark>pPart<\/mark>.msdesc [locusGrp] model.phrase...."}]},{"docId":"TEI.model.paraPart","docUri":"TEI.model.paraPart.html","score":5,"contexts":[{"form":"pPart","weight":"1","pos":98,"context":"...[hi q] ] model.lPart model.<mark>pPart<\/mark>.data [model.addressLike [affiliation]..."},{"form":"pPart","weight":"1","pos":140,"context":"...location] idno objectName rs] ] model.<mark>pPart<\/mark>.edit [model.pPart.editorial [..."},{"form":"pPart","weight":"1","pos":143,"context":"...] model.pPart.edit [model.<mark>pPart<\/mark>.editorial [abbr choice subst] model...."},{"form":"pPart","weight":"1","pos":149,"context":"....editorial [abbr choice subst] model.<mark>pPart<\/mark>.transcriptional [add damage del handShift orig reg..."},{"form":"pPart","weight":"1","pos":161,"context":"...orig reg sic supplied unclear] ] model.<mark>pPart<\/mark>.msdesc [locusGrp] model.phrase...."}]},{"docId":"TEI.model.limitedPhrase","docUri":"TEI.model.limitedPhrase.html","score":3,"contexts":[{"form":"pPart","weight":"1","pos":38,"context":"...] model.hiLike [hi q] model.<mark>pPart<\/mark>.data [model.addressLike [affiliation]..."},{"form":"pPart","weight":"1","pos":80,"context":"...location] idno objectName rs] ] model.<mark>pPart<\/mark>.editorial [abbr choice subst] model...."},{"form":"pPart","weight":"1","pos":86,"context":"....editorial [abbr choice subst] model.<mark>pPart<\/mark>.msdesc [locusGrp] model.phrase...."}]},{"docId":"TEI.model.pPart.edit","docUri":"TEI.model.pPart.edit.html","score":4,"contexts":[{"form":"pPart","weight":"2","pos":2,"context":"model.<mark>pPart<\/mark>.edit"},{"form":"pPart","weight":"1","pos":22,"context":"model.<mark>pPart<\/mark>.editorial [abbr choice subst] model...."},{"form":"pPart","weight":"1","pos":28,"context":"....editorial [abbr choice subst] model.<mark>pPart<\/mark>.transcriptional [add damage del handShift orig reg..."}]},{"docId":"TEI.model.pPart.transcriptional","docUri":"TEI.model.pPart.transcriptional.html","score":3,"contexts":[{"form":"pPart","weight":"2","pos":2,"context":"model.<mark>pPart<\/mark>.transcriptional"},{"form":"pPart","weight":"1","pos":24,"context":"lg model.<mark>pPart<\/mark>.edit","fid":"_d2e88214"}]},{"docId":"TEI.model.pPart.editorial","docUri":"TEI.model.pPart.editorial.html","score":3,"contexts":[{"form":"pPart","weight":"2","pos":2,"context":"model.<mark>pPart<\/mark>.editorial"},{"form":"pPart","weight":"1","pos":24,"context":"model.limitedPhrase model.<mark>pPart<\/mark>.edit","fid":"_d2e88114"}]},{"docId":"TEI.sic","docUri":"TEI.sic.html","score":1,"contexts":[{"form":"pPart","weight":"1","pos":42,"context":"model.choicePart model.<mark>pPart<\/mark>.transcriptional","fid":"_d2e72826"}]},{"docId":"TEI.model.pPart.msdesc","docUri":"TEI.model.pPart.msdesc.html","score":2,"contexts":[{"form":"pPart","weight":"2","pos":2,"context":"model.<mark>pPart<\/mark>.msdesc"}]},{"docId":"TEI.orig","docUri":"TEI.orig.html","score":1,"contexts":[{"form":"pPart","weight":"1","pos":41,"context":"model.choicePart model.<mark>pPart<\/mark>.transcriptional","fid":"_d2e56230"}]},{"docId":"TEI.damage","docUri":"TEI.damage.html","score":1,"contexts":[{"form":"pPart","weight":"1","pos":61,"context":"model.linePart model.<mark>pPart<\/mark>.transcriptional","fid":"_d2e17010"}]},{"docId":"TEI.supplied","docUri":"TEI.supplied.html","score":1,"contexts":[{"form":"pPart","weight":"1","pos":57,"context":"model.choicePart model.<mark>pPart<\/mark>.transcriptional ","fid":"_d2e75361"}]},{"docId":"TEI.locusGrp","docUri":"TEI.locusGrp.html","score":1,"contexts":[{"form":"pPart","weight":"1","pos":62,"context":"model.<mark>pPart<\/mark>.msdesc ","fid":"_d2e45110"}]},{"docId":"TEI.subst","docUri":"TEI.subst.html","score":1,"contexts":[{"form":"pPart","weight":"1","pos":53,"context":"model.<mark>pPart<\/mark>.editorial","fid":"_d2e74514"}]},{"docId":"TEI.model.addressLike","docUri":"TEI.model.addressLike.html","score":1,"contexts":[{"form":"pPart","weight":"1","pos":17,"context":"location model.correspActionPart model.<mark>pPart<\/mark>.data","fid":"_d2e84448"}]},{"docId":"TEI.model.pPart.data","docUri":"TEI.model.pPart.data.html","score":2,"contexts":[{"form":"pPart","weight":"2","pos":2,"context":"model.<mark>pPart<\/mark>.data"}]},{"docId":"TEI.model.dateLike","docUri":"TEI.model.dateLike.html","score":1,"contexts":[{"form":"pPart","weight":"1","pos":18,"context":"imprint model.correspActionPart model.<mark>pPart<\/mark>.data setting","fid":"_d2e85204"}]},{"docId":"TEI.unclear","docUri":"TEI.unclear.html","score":1,"contexts":[{"form":"pPart","weight":"1","pos":138,"context":"model.choicePart model.linePart model.<mark>pPart<\/mark>.transcriptional","fid":"_d2e82811"}]},{"docId":"TEI.model.measureLike","docUri":"TEI.model.measureLike.html","score":1,"contexts":[{"form":"pPart","weight":"1","pos":21,"context":"location model.<mark>pPart<\/mark>.data","fid":"_d2e87237"}]},{"docId":"TEI.del","docUri":"TEI.del.html","score":1,"contexts":[{"form":"pPart","weight":"1","pos":68,"context":"model.linePart model.<mark>pPart<\/mark>.transcriptional ","fid":"_d2e19101"}]},{"docId":"TEI.add","docUri":"TEI.add.html","score":1,"contexts":[{"form":"pPart","weight":"1","pos":65,"context":"model.linePart model.<mark>pPart<\/mark>.transcriptional ","fid":"_d2e7151"}]},{"docId":"TEI.model.nameLike","docUri":"TEI.model.nameLike.html","score":1,"contexts":[{"form":"pPart","weight":"1","pos":14,"context":"model.correspActionPart model.<mark>pPart<\/mark>.data","fid":"_d2e87471"}]},{"docId":"TEI.choice","docUri":"TEI.choice.html","score":1,"contexts":[{"form":"pPart","weight":"1","pos":36,"context":"model.linePart model.<mark>pPart<\/mark>.editorial","fid":"_d2e13768"}]},{"docId":"TEI.handShift","docUri":"TEI.handShift.html","score":1,"contexts":[{"form":"pPart","weight":"1","pos":75,"context":"model.linePart model.<mark>pPart<\/mark>.transcriptional","fid":"_d2e34298"}]},{"docId":"TEI.abbr","docUri":"TEI.abbr.html","score":1,"contexts":[{"form":"pPart","weight":"1","pos":138,"context":"model.choicePart model.<mark>pPart<\/mark>.editorial","fid":"_d2e5888"}]},{"docId":"TEI.reg","docUri":"TEI.reg.html","score":1,"contexts":[{"form":"pPart","weight":"1","pos":43,"context":"model.choicePart model.<mark>pPart<\/mark>.transcriptional","fid":"_d2e65580"}]}]}