{"stem":"size","instances":[{"docId":"TEI.extent","docUri":"TEI.extent.html","score":4,"contexts":[{"form":"size","weight":"1","pos":5,"context":"(extent) describes the approximate <mark>size<\/mark> of a text stored on some carrier medium or...","fid":"_d2e25629"},{"form":"Size","weight":"1","pos":28,"context":"...The File Description 3.12.2.4. Imprint, <mark>Size<\/mark> of a Document, and Reprint Information 10.7.1....","fid":"_d2e25629"},{"form":"size","weight":"1","pos":142,"context":"...to supply normalized or machine tractable versions of the <mark>size<\/mark> or sizes concerned. "},{"form":"sizes","weight":"1","pos":143,"context":"...normalized or machine tractable versions of the size or <mark>sizes<\/mark> concerned. "}]},{"docId":"TEI.att.dimensions","docUri":"TEI.att.dimensions.html","score":2,"contexts":[{"form":"size","weight":"1","pos":6,"context":" provides attributes for describing the <mark>size<\/mark> of physical objects.","fid":"_d2e92049"},{"form":"size","weight":"1","pos":57,"context":"indicates the <mark>size<\/mark> of the object concerned using a project-specific..."}]},{"docId":"TEI.pubPlace","docUri":"TEI.pubPlace.html","score":1,"contexts":[{"form":"Size","weight":"1","pos":13,"context":"...published. [3.12.2.4. Imprint, <mark>Size<\/mark> of a Document, and Reprint Information]","fid":"_d2e62347"}]},{"docId":"TEI.idno","docUri":"TEI.idno.html","score":1,"contexts":[{"form":"Size","weight":"1","pos":31,"context":"...The Series Statement 3.12.2.4. Imprint, <mark>Size<\/mark> of a Document, and Reprint Information]","fid":"_d2e35999"}]},{"docId":"TEI.teidata.outputMeasurement","docUri":"TEI.teidata.outputMeasurement.html","score":1,"contexts":[{"form":"size","weight":"1","pos":8,"context":"...a range of values for use in specifying the <mark>size<\/mark> of an object that is intended for display....","fid":"_d2e100987"}]},{"docId":"TEI.publisher","docUri":"TEI.publisher.html","score":1,"contexts":[{"form":"Size","weight":"1","pos":14,"context":"...item. [3.12.2.4. Imprint, <mark>Size<\/mark> of a Document, and Reprint Information 2.2.4....","fid":"_d2e62850"}]},{"docId":"TEI.date","docUri":"TEI.date.html","score":1,"contexts":[{"form":"Size","weight":"1","pos":20,"context":"...The Revision Description 3.12.2.4. Imprint, <mark>Size<\/mark> of a Document, and Reprint Information 15.2.3....","fid":"_d2e17644"}]},{"docId":"TEI.att.media","docUri":"TEI.att.media.html","score":1,"contexts":[{"form":"size","weight":"1","pos":44,"context":"...factor to be applied when generating the desired display <mark>size<\/mark>             "}]},{"docId":"TEI.imprint","docUri":"TEI.imprint.html","score":1,"contexts":[{"form":"Size","weight":"1","pos":12,"context":"...item. [3.12.2.4. Imprint, <mark>Size<\/mark> of a Document, and Reprint Information]","fid":"_d2e37036"}]},{"docId":"encoding_structure","docUri":"encoding_structure.html","score":20,"contexts":[{"form":"size","weight":"20","pos":40,"context":"...differently, any renditional information about the heading (i.e. <mark>size<\/mark> or alignment) must be specified using the rendition...","fid":"_d2e1605"}]}]}