{"stem":"subst","instances":[{"docId":"TEI.del","docUri":"TEI.del.html","score":2,"contexts":[{"form":"subst","weight":"1","pos":159,"context":"transcr: damage fw <mark>subst<\/mark> supplied zone","fid":"_d2e19377"},{"form":"subst","weight":"1","pos":241,"context":"transcr: damage fw handShift <mark>subst<\/mark> supplied","fid":"_d2e19626"}]},{"docId":"TEI.add","docUri":"TEI.add.html","score":2,"contexts":[{"form":"subst","weight":"1","pos":156,"context":"transcr: damage fw <mark>subst<\/mark> supplied zone","fid":"_d2e7427"},{"form":"subst","weight":"1","pos":238,"context":"transcr: damage fw handShift <mark>subst<\/mark> supplied","fid":"_d2e7676"}]},{"docId":"TEI.fw","docUri":"TEI.fw.html","score":2,"contexts":[{"form":"subst","weight":"1","pos":215,"context":"transcr: damage fw <mark>subst<\/mark> supplied surface surfaceGrp zone","fid":"_d2e30049"},{"form":"subst","weight":"1","pos":286,"context":"transcr: damage fw handShift <mark>subst<\/mark> supplied","fid":"_d2e30261"}]},{"docId":"transcribing_editing","docUri":"transcribing_editing.html","score":40,"contexts":[{"form":"subst","weight":"20","pos":385,"context":"...wrapping the add and del with the substitution element <mark>subst<\/mark>. For example:","fid":"_d2e2901"},{"form":"subst","weight":"20","pos":421,"context":"...we wrap the add and the del in a <mark>subst<\/mark>. So putting this all together:","fid":"_d2e2948"}]},{"docId":"TEI.label","docUri":"TEI.label.html","score":1,"contexts":[{"form":"subst","weight":"1","pos":171,"context":"transcr: damage fw handShift <mark>subst<\/mark> supplied","fid":"_d2e38553"}]},{"docId":"TEI.dateline","docUri":"TEI.dateline.html","score":1,"contexts":[{"form":"subst","weight":"1","pos":129,"context":"transcr: damage fw handShift <mark>subst<\/mark> supplied","fid":"_d2e18556"}]},{"docId":"TEI.p","docUri":"TEI.p.html","score":1,"contexts":[{"form":"subst","weight":"1","pos":167,"context":"transcr: damage fw handShift <mark>subst<\/mark> supplied","fid":"_d2e57723"}]},{"docId":"TEI.orgName","docUri":"TEI.orgName.html","score":1,"contexts":[{"form":"subst","weight":"1","pos":293,"context":"transcr: damage fw handShift <mark>subst<\/mark> supplied","fid":"_d2e56083"}]},{"docId":"TEI.lb","docUri":"TEI.lb.html","score":1,"contexts":[{"form":"subst","weight":"1","pos":161,"context":"transcr: damage fw <mark>subst<\/mark> supplied surface surfaceGrp zone","fid":"_d2e40203"}]},{"docId":"TEI.title","docUri":"TEI.title.html","score":1,"contexts":[{"form":"subst","weight":"1","pos":477,"context":"transcr: damage fw handShift <mark>subst<\/mark> supplied","fid":"_d2e81182"}]},{"docId":"TEI.sic","docUri":"TEI.sic.html","score":1,"contexts":[{"form":"subst","weight":"1","pos":214,"context":"transcr: damage fw handShift <mark>subst<\/mark> supplied","fid":"_d2e73347"}]},{"docId":"TEI.w","docUri":"TEI.w.html","score":1,"contexts":[{"form":"subst","weight":"1","pos":161,"context":"transcr: damage fw handShift <mark>subst<\/mark> supplied","fid":"_d2e83934"}]},{"docId":"TEI.att.global.source","docUri":"TEI.att.global.source.html","score":1,"contexts":[{"form":"subst","weight":"1","pos":175,"context":"...rs salute setting settingDesc settlement sic signed sourceDesc standOff <mark>subst<\/mark> summary supportDesc surface surfaceGrp surname surrogates table tagsDecl taxonomy..."}]},{"docId":"TEI.langKnown","docUri":"TEI.langKnown.html","score":1,"contexts":[{"form":"subst","weight":"1","pos":191,"context":"transcr: fw <mark>subst<\/mark>","fid":"_d2e39278"}]},{"docId":"TEI.att.global.rendition","docUri":"TEI.att.global.rendition.html","score":1,"contexts":[{"form":"subst","weight":"1","pos":171,"context":"...rs salute setting settingDesc settlement sic signed sourceDesc standOff <mark>subst<\/mark> summary supportDesc surface surfaceGrp surname surrogates table tagsDecl taxonomy..."}]},{"docId":"TEI.rule","docUri":"TEI.rule.html","score":1,"contexts":[{"form":"subst","weight":"1","pos":197,"context":"transcr: damage fw <mark>subst<\/mark> supplied surface surfaceGrp zone","fid":"_d2e70296"}]},{"docId":"TEI.addName","docUri":"TEI.addName.html","score":1,"contexts":[{"form":"subst","weight":"1","pos":219,"context":"transcr: damage fw handShift <mark>subst<\/mark> supplied","fid":"_d2e8317"}]},{"docId":"TEI.surname","docUri":"TEI.surname.html","score":1,"contexts":[{"form":"subst","weight":"1","pos":214,"context":"transcr: damage fw handShift <mark>subst<\/mark> supplied","fid":"_d2e77248"}]},{"docId":"TEI.objectName","docUri":"TEI.objectName.html","score":1,"contexts":[{"form":"subst","weight":"1","pos":296,"context":"transcr: damage fw handShift <mark>subst<\/mark> supplied","fid":"_d2e54375"}]},{"docId":"TEI.genName","docUri":"TEI.genName.html","score":1,"contexts":[{"form":"subst","weight":"1","pos":221,"context":"transcr: damage fw handShift <mark>subst<\/mark> supplied","fid":"_d2e32059"}]},{"docId":"TEI.language","docUri":"TEI.language.html","score":1,"contexts":[{"form":"subst","weight":"1","pos":119,"context":"transcr: fw <mark>subst<\/mark>","fid":"_d2e39711"}]},{"docId":"TEI.num","docUri":"TEI.num.html","score":1,"contexts":[{"form":"subst","weight":"1","pos":259,"context":"transcr: damage fw handShift <mark>subst<\/mark> supplied","fid":"_d2e53255"}]},{"docId":"TEI.rs","docUri":"TEI.rs.html","score":1,"contexts":[{"form":"subst","weight":"1","pos":280,"context":"transcr: damage fw handShift <mark>subst<\/mark> supplied","fid":"_d2e69725"}]},{"docId":"TEI.pubPlace","docUri":"TEI.pubPlace.html","score":1,"contexts":[{"form":"subst","weight":"1","pos":121,"context":"transcr: damage fw handShift <mark>subst<\/mark> supplied","fid":"_d2e62627"}]},{"docId":"TEI.activity","docUri":"TEI.activity.html","score":1,"contexts":[{"form":"subst","weight":"1","pos":91,"context":"transcr: fw <mark>subst<\/mark>","fid":"_d2e7004"}]},{"docId":"TEI.faith","docUri":"TEI.faith.html","score":1,"contexts":[{"form":"subst","weight":"1","pos":177,"context":"transcr: damage fw handShift <mark>subst<\/mark> supplied","fid":"_d2e26449"}]},{"docId":"TEI.quote","docUri":"TEI.quote.html","score":1,"contexts":[{"form":"subst","weight":"1","pos":222,"context":"transcr: damage fw handShift <mark>subst<\/mark> supplied","fid":"_d2e64750"}]},{"docId":"TEI.settlement","docUri":"TEI.settlement.html","score":1,"contexts":[{"form":"subst","weight":"1","pos":295,"context":"transcr: damage fw handShift <mark>subst<\/mark> supplied","fid":"_d2e72366"}]},{"docId":"TEI.att.global","docUri":"TEI.att.global.html","score":1,"contexts":[{"form":"subst","weight":"1","pos":167,"context":"...rs salute setting settingDesc settlement sic signed sourceDesc standOff <mark>subst<\/mark> summary supportDesc surface surfaceGrp surname surrogates table tagsDecl taxonomy..."}]},{"docId":"TEI.enclosure","docUri":"TEI.enclosure.html","score":1,"contexts":[{"form":"subst","weight":"1","pos":105,"context":"transcr: damage fw handShift <mark>subst<\/mark> supplied","fid":"_d2e24807"}]},{"docId":"TEI.mentioned","docUri":"TEI.mentioned.html","score":1,"contexts":[{"form":"subst","weight":"1","pos":196,"context":"transcr: damage fw handShift <mark>subst<\/mark> supplied","fid":"_d2e46173"}]},{"docId":"TEI.byline","docUri":"TEI.byline.html","score":1,"contexts":[{"form":"subst","weight":"1","pos":126,"context":"transcr: damage fw handShift <mark>subst<\/mark> supplied","fid":"_d2e11865"}]},{"docId":"TEI.pb","docUri":"TEI.pb.html","score":1,"contexts":[{"form":"subst","weight":"1","pos":150,"context":"transcr: damage fw <mark>subst<\/mark> supplied surface surfaceGrp zone","fid":"_d2e58194"}]},{"docId":"TEI.l","docUri":"TEI.l.html","score":1,"contexts":[{"form":"subst","weight":"1","pos":176,"context":"transcr: damage fw handShift <mark>subst<\/mark> supplied","fid":"_d2e38060"}]},{"docId":"TEI.nameLink","docUri":"TEI.nameLink.html","score":1,"contexts":[{"form":"subst","weight":"1","pos":209,"context":"transcr: damage fw handShift <mark>subst<\/mark> supplied","fid":"_d2e49738"}]},{"docId":"TEI.sex","docUri":"TEI.sex.html","score":1,"contexts":[{"form":"subst","weight":"1","pos":103,"context":"transcr: damage fw handShift <mark>subst<\/mark> supplied","fid":"_d2e72690"}]},{"docId":"TEI.author","docUri":"TEI.author.html","score":1,"contexts":[{"form":"subst","weight":"1","pos":205,"context":"transcr: damage fw handShift <mark>subst<\/mark> supplied","fid":"_d2e9796"}]},{"docId":"TEI.orig","docUri":"TEI.orig.html","score":1,"contexts":[{"form":"subst","weight":"1","pos":213,"context":"transcr: damage fw handShift <mark>subst<\/mark> supplied","fid":"_d2e56751"}]},{"docId":"TEI.floruit","docUri":"TEI.floruit.html","score":1,"contexts":[{"form":"subst","weight":"1","pos":192,"context":"transcr: damage fw handShift <mark>subst<\/mark> supplied","fid":"_d2e27967"}]},{"docId":"TEI.persName","docUri":"TEI.persName.html","score":1,"contexts":[{"form":"subst","weight":"1","pos":312,"context":"transcr: damage fw handShift <mark>subst<\/mark> supplied","fid":"_d2e59412"}]},{"docId":"TEI.residence","docUri":"TEI.residence.html","score":1,"contexts":[{"form":"subst","weight":"1","pos":135,"context":"transcr: damage fw handShift <mark>subst<\/mark> supplied","fid":"_d2e67572"}]},{"docId":"TEI.docEdition","docUri":"TEI.docEdition.html","score":1,"contexts":[{"form":"subst","weight":"1","pos":123,"context":"transcr: damage fw handShift <mark>subst<\/mark> supplied","fid":"_d2e22026"}]},{"docId":"TEI.docImprint","docUri":"TEI.docImprint.html","score":1,"contexts":[{"form":"subst","weight":"1","pos":118,"context":"transcr: damage fw handShift <mark>subst<\/mark> supplied","fid":"_d2e22354"}]},{"docId":"TEI.note","docUri":"TEI.note.html","score":1,"contexts":[{"form":"subst","weight":"1","pos":322,"context":"transcr: damage fw handShift <mark>subst<\/mark> supplied","fid":"_d2e51165"}]},{"docId":"TEI.nationality","docUri":"TEI.nationality.html","score":1,"contexts":[{"form":"subst","weight":"1","pos":247,"context":"transcr: damage fw handShift <mark>subst<\/mark> supplied","fid":"_d2e50187"}]},{"docId":"TEI.term","docUri":"TEI.term.html","score":1,"contexts":[{"form":"subst","weight":"1","pos":214,"context":"transcr: damage fw handShift <mark>subst<\/mark> supplied","fid":"_d2e79356"}]},{"docId":"TEI.figDesc","docUri":"TEI.figDesc.html","score":1,"contexts":[{"form":"subst","weight":"1","pos":96,"context":"transcr: <mark>subst<\/mark>","fid":"_d2e26784"}]},{"docId":"TEI.publisher","docUri":"TEI.publisher.html","score":1,"contexts":[{"form":"subst","weight":"1","pos":124,"context":"transcr: damage fw handShift <mark>subst<\/mark> supplied","fid":"_d2e63126"}]},{"docId":"TEI.occupation","docUri":"TEI.occupation.html","score":1,"contexts":[{"form":"subst","weight":"1","pos":253,"context":"transcr: damage fw handShift <mark>subst<\/mark> supplied","fid":"_d2e54933"}]},{"docId":"TEI.time","docUri":"TEI.time.html","score":1,"contexts":[{"form":"subst","weight":"1","pos":192,"context":"transcr: damage fw handShift <mark>subst<\/mark> supplied","fid":"_d2e80344"}]},{"docId":"TEI.damage","docUri":"TEI.damage.html","score":1,"contexts":[{"form":"subst","weight":"1","pos":233,"context":"transcr: damage fw handShift <mark>subst<\/mark> supplied","fid":"_d2e17531"}]},{"docId":"TEI.att.dimensions","docUri":"TEI.att.dimensions.html","score":1,"contexts":[{"form":"subst","weight":"1","pos":18,"context":"...damaged [damage] add del ellipsis floruit gap <mark>subst<\/mark> unclear"}]},{"docId":"TEI.supplied","docUri":"TEI.supplied.html","score":1,"contexts":[{"form":"subst","weight":"1","pos":230,"context":"transcr: damage fw handShift <mark>subst<\/mark> supplied","fid":"_d2e75886"}]},{"docId":"TEI.placeName","docUri":"TEI.placeName.html","score":1,"contexts":[{"form":"subst","weight":"1","pos":300,"context":"transcr: damage fw handShift <mark>subst<\/mark> supplied","fid":"_d2e61046"}]},{"docId":"TEI.subst","docUri":"TEI.subst.html","score":2,"contexts":[{"form":"subst","weight":"2","pos":1,"context":"&lt;<mark>subst<\/mark>&gt;"}]},{"docId":"TEI.model.limitedPhrase","docUri":"TEI.model.limitedPhrase.html","score":1,"contexts":[{"form":"subst","weight":"1","pos":84,"context":"...] model.pPart.editorial [abbr choice <mark>subst<\/mark>] model.pPart.msdesc [locusGrp]..."}]},{"docId":"TEI.gloss","docUri":"TEI.gloss.html","score":1,"contexts":[{"form":"subst","weight":"1","pos":213,"context":"transcr: damage fw handShift <mark>subst<\/mark> supplied","fid":"_d2e33113"}]},{"docId":"TEI.head","docUri":"TEI.head.html","score":1,"contexts":[{"form":"subst","weight":"1","pos":405,"context":"transcr: damage fw handShift <mark>subst<\/mark> supplied","fid":"_d2e35060"}]},{"docId":"TEI.collection","docUri":"TEI.collection.html","score":1,"contexts":[{"form":"subst","weight":"1","pos":99,"context":"transcr: fw <mark>subst<\/mark>","fid":"_d2e15119"}]},{"docId":"TEI.repository","docUri":"TEI.repository.html","score":1,"contexts":[{"form":"subst","weight":"1","pos":97,"context":"transcr: fw <mark>subst<\/mark>","fid":"_d2e66811"}]},{"docId":"TEI.handNote","docUri":"TEI.handNote.html","score":1,"contexts":[{"form":"subst","weight":"1","pos":150,"context":"transcr: damage fw handShift <mark>subst<\/mark> supplied","fid":"_d2e34032"}]},{"docId":"TEI.compliment","docUri":"TEI.compliment.html","score":1,"contexts":[{"form":"subst","weight":"1","pos":111,"context":"transcr: damage fw handShift <mark>subst<\/mark> supplied","fid":"_d2e15479"}]},{"docId":"TEI.emph","docUri":"TEI.emph.html","score":1,"contexts":[{"form":"subst","weight":"1","pos":222,"context":"transcr: damage fw handShift <mark>subst<\/mark> supplied","fid":"_d2e24454"}]},{"docId":"TEI.roleName","docUri":"TEI.roleName.html","score":1,"contexts":[{"form":"subst","weight":"1","pos":218,"context":"transcr: damage fw handShift <mark>subst<\/mark> supplied","fid":"_d2e68914"}]},{"docId":"TEI.hi","docUri":"TEI.hi.html","score":1,"contexts":[{"form":"subst","weight":"1","pos":230,"context":"transcr: damage fw handShift <mark>subst<\/mark> supplied","fid":"_d2e35808"}]},{"docId":"TEI.origin","docUri":"TEI.origin.html","score":1,"contexts":[{"form":"subst","weight":"1","pos":197,"context":"transcr: damage fw handShift <mark>subst<\/mark> supplied","fid":"_d2e57204"}]},{"docId":"TEI.change","docUri":"TEI.change.html","score":1,"contexts":[{"form":"subst","weight":"1","pos":252,"context":"transcr: damage fw handShift <mark>subst<\/mark> supplied","fid":"_d2e13307"}]},{"docId":"TEI.att.ranging","docUri":"TEI.att.ranging.html","score":1,"contexts":[{"form":"subst","weight":"1","pos":19,"context":"...damaged [damage] add del ellipsis floruit gap <mark>subst<\/mark> unclear] num"}]},{"docId":"TEI.catDesc","docUri":"TEI.catDesc.html","score":1,"contexts":[{"form":"subst","weight":"1","pos":87,"context":"transcr: <mark>subst<\/mark>","fid":"_d2e12127"}]},{"docId":"TEI.desc","docUri":"TEI.desc.html","score":1,"contexts":[{"form":"subst","weight":"1","pos":197,"context":"transcr: <mark>subst<\/mark>","fid":"_d2e20221"}]},{"docId":"TEI.duration","docUri":"TEI.duration.html","score":1,"contexts":[{"form":"subst","weight":"1","pos":86,"context":"transcr: damage fw handShift <mark>subst<\/mark> supplied","fid":"_d2e22895"}]},{"docId":"TEI.corr","docUri":"TEI.corr.html","score":1,"contexts":[{"form":"subst","weight":"1","pos":128,"context":"transcr: damage fw handShift <mark>subst<\/mark> supplied","fid":"_d2e15885"}]},{"docId":"TEI.unclear","docUri":"TEI.unclear.html","score":1,"contexts":[{"form":"subst","weight":"1","pos":311,"context":"transcr: damage fw handShift <mark>subst<\/mark> supplied","fid":"_d2e83338"}]},{"docId":"TEI.editor","docUri":"TEI.editor.html","score":1,"contexts":[{"form":"subst","weight":"1","pos":201,"context":"transcr: damage fw handShift <mark>subst<\/mark> supplied","fid":"_d2e23270"}]},{"docId":"TEI.salute","docUri":"TEI.salute.html","score":1,"contexts":[{"form":"subst","weight":"1","pos":139,"context":"transcr: damage fw handShift <mark>subst<\/mark> supplied","fid":"_d2e70843"}]},{"docId":"TEI.expan","docUri":"TEI.expan.html","score":1,"contexts":[{"form":"subst","weight":"1","pos":107,"context":"transcr: damage fw handShift <mark>subst<\/mark> supplied","fid":"_d2e25557"}]},{"docId":"TEI.cell","docUri":"TEI.cell.html","score":1,"contexts":[{"form":"subst","weight":"1","pos":118,"context":"transcr: damage fw handShift <mark>subst<\/mark> supplied","fid":"_d2e12811"}]},{"docId":"TEI.model.pPart.editorial","docUri":"TEI.model.pPart.editorial.html","score":1,"contexts":[{"form":"subst","weight":"1","pos":28,"context":"abbr choice <mark>subst<\/mark>"}]},{"docId":"TEI.surrogates","docUri":"TEI.surrogates.html","score":1,"contexts":[{"form":"subst","weight":"1","pos":120,"context":"transcr: damage fw handShift <mark>subst<\/mark> supplied","fid":"_d2e77604"}]},{"docId":"TEI.imprimatur","docUri":"TEI.imprimatur.html","score":1,"contexts":[{"form":"subst","weight":"1","pos":123,"context":"transcr: damage fw handShift <mark>subst<\/mark> supplied","fid":"_d2e36986"}]},{"docId":"TEI.death","docUri":"TEI.death.html","score":1,"contexts":[{"form":"subst","weight":"1","pos":122,"context":"transcr: damage fw handShift <mark>subst<\/mark> supplied","fid":"_d2e18918"}]},{"docId":"TEI.rendition","docUri":"TEI.rendition.html","score":1,"contexts":[{"form":"subst","weight":"1","pos":211,"context":"transcr: <mark>subst<\/mark>","fid":"_d2e66497"}]},{"docId":"TEI.extent","docUri":"TEI.extent.html","score":1,"contexts":[{"form":"subst","weight":"1","pos":129,"context":"transcr: damage fw handShift <mark>subst<\/mark> supplied","fid":"_d2e25900"}]},{"docId":"TEI.docAuthor","docUri":"TEI.docAuthor.html","score":1,"contexts":[{"form":"subst","weight":"1","pos":128,"context":"transcr: damage fw handShift <mark>subst<\/mark> supplied","fid":"_d2e21234"}]},{"docId":"TEI.affiliation","docUri":"TEI.affiliation.html","score":1,"contexts":[{"form":"subst","weight":"1","pos":316,"context":"transcr: damage fw handShift <mark>subst<\/mark> supplied","fid":"_d2e9318"}]},{"docId":"TEI.milestone","docUri":"TEI.milestone.html","score":1,"contexts":[{"form":"subst","weight":"1","pos":195,"context":"transcr: damage fw <mark>subst<\/mark> supplied surface surfaceGrp zone","fid":"_d2e46840"}]},{"docId":"TEI.foreign","docUri":"TEI.foreign.html","score":1,"contexts":[{"form":"subst","weight":"1","pos":202,"context":"transcr: damage fw handShift <mark>subst<\/mark> supplied","fid":"_d2e28581"}]},{"docId":"TEI.date","docUri":"TEI.date.html","score":1,"contexts":[{"form":"subst","weight":"1","pos":217,"context":"transcr: damage fw handShift <mark>subst<\/mark> supplied","fid":"_d2e18218"}]},{"docId":"TEI.signed","docUri":"TEI.signed.html","score":1,"contexts":[{"form":"subst","weight":"1","pos":140,"context":"transcr: damage fw handShift <mark>subst<\/mark> supplied","fid":"_d2e73767"}]},{"docId":"TEI.resp","docUri":"TEI.resp.html","score":1,"contexts":[{"form":"subst","weight":"1","pos":183,"context":"transcr: fw <mark>subst<\/mark>","fid":"_d2e67942"}]},{"docId":"TEI.ab","docUri":"TEI.ab.html","score":1,"contexts":[{"form":"subst","weight":"1","pos":185,"context":"transcr: damage fw handShift <mark>subst<\/mark> supplied","fid":"_d2e5667"}]},{"docId":"TEI.model.phrase","docUri":"TEI.model.phrase.html","score":1,"contexts":[{"form":"subst","weight":"1","pos":96,"context":"...[model.pPart.editorial [abbr choice <mark>subst<\/mark>] model.pPart.transcriptional [add damage..."}]},{"docId":"TEI.docDate","docUri":"TEI.docDate.html","score":1,"contexts":[{"form":"subst","weight":"1","pos":147,"context":"transcr: damage fw handShift <mark>subst<\/mark> supplied","fid":"_d2e21648"}]},{"docId":"TEI.lim.att.global.fragmentable","docUri":"TEI.lim.att.global.fragmentable.html","score":1,"contexts":[{"form":"subst","weight":"1","pos":170,"context":"...rs salute setting settingDesc settlement sic signed sourceDesc standOff <mark>subst<\/mark> summary supportDesc surface surfaceGrp surname surrogates table tagsDecl taxonomy..."}]},{"docId":"TEI.noteMarker","docUri":"TEI.noteMarker.html","score":1,"contexts":[{"form":"subst","weight":"1","pos":225,"context":"transcr: damage fw <mark>subst<\/mark> supplied surface surfaceGrp zone","fid":"_d2e52337"}]},{"docId":"TEI.seg","docUri":"TEI.seg.html","score":1,"contexts":[{"form":"subst","weight":"1","pos":105,"context":"transcr: damage fw handShift <mark>subst<\/mark> supplied","fid":"_d2e71369"}]},{"docId":"TEI.model.pPart.edit","docUri":"TEI.model.pPart.edit.html","score":1,"contexts":[{"form":"subst","weight":"1","pos":26,"context":"model.pPart.editorial [abbr choice <mark>subst<\/mark>] model.pPart.transcriptional [add damage..."}]},{"docId":"TEI.trailer","docUri":"TEI.trailer.html","score":1,"contexts":[{"form":"subst","weight":"1","pos":141,"context":"transcr: damage fw handShift <mark>subst<\/mark> supplied","fid":"_d2e82562"}]},{"docId":"TEI.name","docUri":"TEI.name.html","score":1,"contexts":[{"form":"subst","weight":"1","pos":318,"context":"transcr: damage fw handShift <mark>subst<\/mark> supplied","fid":"_d2e49049"}]},{"docId":"TEI.item","docUri":"TEI.item.html","score":1,"contexts":[{"form":"subst","weight":"1","pos":119,"context":"transcr: damage fw handShift <mark>subst<\/mark> supplied","fid":"_d2e37519"}]},{"docId":"TEI.birth","docUri":"TEI.birth.html","score":1,"contexts":[{"form":"subst","weight":"1","pos":122,"context":"transcr: damage fw handShift <mark>subst<\/mark> supplied","fid":"_d2e11125"}]},{"docId":"TEI.q","docUri":"TEI.q.html","score":1,"contexts":[{"form":"subst","weight":"1","pos":224,"context":"transcr: damage fw handShift <mark>subst<\/mark> supplied","fid":"_d2e63978"}]},{"docId":"TEI.forename","docUri":"TEI.forename.html","score":1,"contexts":[{"form":"subst","weight":"1","pos":210,"context":"transcr: damage fw handShift <mark>subst<\/mark> supplied","fid":"_d2e29226"}]},{"docId":"TEI.model.milestoneLike","docUri":"TEI.model.milestoneLike.html","score":1,"contexts":[{"form":"subst","weight":"1","pos":26,"context":"...lim.macro.openerAndCloserContent listBibl model.global <mark>subst<\/mark>","fid":"_d2e87288"}]},{"docId":"TEI.bibl","docUri":"TEI.bibl.html","score":1,"contexts":[{"form":"subst","weight":"1","pos":190,"context":"transcr: damage fw handShift <mark>subst<\/mark> supplied","fid":"_d2e10355"}]},{"docId":"TEI.titlePart","docUri":"TEI.titlePart.html","score":1,"contexts":[{"form":"subst","weight":"1","pos":161,"context":"transcr: damage fw handShift <mark>subst<\/mark> supplied","fid":"_d2e81971"}]},{"docId":"TEI.ref","docUri":"TEI.ref.html","score":1,"contexts":[{"form":"subst","weight":"1","pos":233,"context":"transcr: damage fw handShift <mark>subst<\/mark> supplied","fid":"_d2e65429"}]},{"docId":"TEI.abbr","docUri":"TEI.abbr.html","score":1,"contexts":[{"form":"subst","weight":"1","pos":307,"context":"transcr: damage fw handShift <mark>subst<\/mark> supplied","fid":"_d2e6394"}]},{"docId":"TEI.reg","docUri":"TEI.reg.html","score":1,"contexts":[{"form":"subst","weight":"1","pos":215,"context":"transcr: damage fw handShift <mark>subst<\/mark> supplied","fid":"_d2e66101"}]},{"docId":"TEI.model.paraPart","docUri":"TEI.model.paraPart.html","score":1,"contexts":[{"form":"subst","weight":"1","pos":147,"context":"...[model.pPart.editorial [abbr choice <mark>subst<\/mark>] model.pPart.transcriptional [add damage..."}]},{"docId":"TEI.summary","docUri":"TEI.summary.html","score":1,"contexts":[{"form":"subst","weight":"1","pos":131,"context":"transcr: damage fw handShift <mark>subst<\/mark> supplied","fid":"_d2e75252"}]},{"docId":"TEI.request","docUri":"TEI.request.html","score":1,"contexts":[{"form":"subst","weight":"1","pos":111,"context":"transcr: damage fw handShift <mark>subst<\/mark> supplied","fid":"_d2e67166"}]}]}