{"stem":"updat","instances":[{"docId":"workflow","docUri":"workflow.html","score":61,"contexts":[{"form":"update","weight":"20","pos":139,"context":"\"Pulling\" from the upstream repository to <mark>update<\/mark> your fork (i.e. getting the most up-to-date version...","fid":"_d2e644"},{"form":"Update","weight":"20","pos":162,"context":"<mark>Update<\/mark> your local copy of the repository by merging any...","fid":"_d2e662"},{"form":"update","weight":"20","pos":570,"context":"...Add a title and a comment to provide an <mark>update<\/mark> about the work. Click on “create a pull...","fid":"_d2e841"},{"form":"Updating","weight":"1","pos":160,"context":"<mark>Updating<\/mark> your Repository","fid":"workflow_updating-your-repository"}]},{"docId":"transcription_workflow","docUri":"transcription_workflow.html","score":21,"contexts":[{"form":"update","weight":"20","pos":92,"context":"...(see Getting Started) and that you have <mark>update<\/mark> your local version of the repository (see Workflow...","fid":"_d2e865"},{"form":"Update","weight":"1","pos":78,"context":"Step 0: <mark>Update<\/mark> your repository","fid":"transcription_workflow_step-0-update-your-repository"}]}]}